{
    "compos": [
        {
            "column_max": 494,
            "row_min": 0,
            "height": 800,
            "id": 0,
            "column_min": 0,
            "row_max": 800,
            "class": "Background",
            "width": 494
        },
        {
            "column_max": 98,
            "row_min": 18,
            "height": 16,
            "id": null,
            "column_min": 25,
            "row_max": 33,
            "class": "Compo",
            "width": 74
        },
        {
            "column_max": 200,
            "row_min": 18,
            "height": 16,
            "id": null,
            "column_min": 168,
            "row_max": 33,
            "class": "Compo",
            "width": 33
        },
        {
            "column_max": 350,
            "row_min": 18,
            "height": 16,
            "id": null,
            "column_min": 266,
            "row_max": 33,
            "class": "Compo",
            "width": 85
        },
        {
            "column_max": 453,
            "row_min": 18,
            "height": 16,
            "id": null,
            "column_min": 410,
            "row_max": 33,
            "class": "Compo",
            "width": 44
        },
        {
            "column_max": 492,
            "row_min": 44,
            "height": 196,
            "id": null,
            "column_min": 0,
            "row_max": 239,
            "class": "Compo",
            "width": 493
        },
        {
            "column_max": 344,
            "row_min": 65,
            "height": 42,
            "id": null,
            "column_min": 262,
            "row_max": 106,
            "class": "Compo",
            "width": 83
        },
        {
            "column_max": 406,
            "row_min": 62,
            "height": 34,
            "id": null,
            "column_min": 373,
            "row_max": 95,
            "class": "Compo",
            "width": 34
        },
        {
            "column_max": 465,
            "row_min": 65,
            "height": 16,
            "id": null,
            "column_min": 445,
            "row_max": 80,
            "class": "Compo",
            "width": 21
        },
        {
            "column_max": 466,
            "row_min": 81,
            "height": 14,
            "id": null,
            "column_min": 433,
            "row_max": 94,
            "class": "Compo",
            "width": 34
        },
        {
            "column_max": 464,
            "row_min": 95,
            "height": 12,
            "id": null,
            "column_min": 442,
            "row_max": 106,
            "class": "Compo",
            "width": 23
        },
        {
            "column_max": 372,
            "row_min": 116,
            "height": 11,
            "id": null,
            "column_min": 353,
            "row_max": 126,
            "class": "Compo",
            "width": 20
        },
        {
            "column_max": 265,
            "row_min": 139,
            "height": 12,
            "id": null,
            "column_min": 219,
            "row_max": 150,
            "class": "Compo",
            "width": 47
        },
        {
            "column_max": 431,
            "row_min": 139,
            "height": 30,
            "id": null,
            "column_min": 406,
            "row_max": 168,
            "class": "Compo",
            "width": 26
        },
        {
            "column_max": 262,
            "row_min": 153,
            "height": 35,
            "id": null,
            "column_min": 219,
            "row_max": 187,
            "class": "Compo",
            "width": 44
        },
        {
            "column_max": 325,
            "row_min": 153,
            "height": 35,
            "id": null,
            "column_min": 268,
            "row_max": 187,
            "class": "Compo",
            "width": 58
        },
        {
            "column_max": 361,
            "row_min": 154,
            "height": 11,
            "id": null,
            "column_min": 348,
            "row_max": 164,
            "class": "Compo",
            "width": 14
        },
        {
            "column_max": 382,
            "row_min": 159,
            "height": 19,
            "id": null,
            "column_min": 363,
            "row_max": 177,
            "class": "Compo",
            "width": 20
        },
        {
            "column_max": 434,
            "row_min": 172,
            "height": 28,
            "id": null,
            "column_min": 405,
            "row_max": 199,
            "class": "Compo",
            "width": 30
        },
        {
            "column_max": 347,
            "row_min": 171,
            "height": 24,
            "id": null,
            "column_min": 329,
            "row_max": 194,
            "class": "Compo",
            "width": 19
        },
        {
            "column_max": 237,
            "row_min": 194,
            "height": 12,
            "id": null,
            "column_min": 219,
            "row_max": 205,
            "class": "Compo",
            "width": 19
        },
        {
            "column_max": 431,
            "row_min": 205,
            "height": 29,
            "id": null,
            "column_min": 406,
            "row_max": 233,
            "class": "Compo",
            "width": 26
        },
        {
            "column_max": 223,
            "row_min": 274,
            "height": 22,
            "id": null,
            "column_min": 180,
            "row_max": 295,
            "class": "Compo",
            "width": 44
        },
        {
            "column_max": 313,
            "row_min": 274,
            "height": 27,
            "id": null,
            "column_min": 226,
            "row_max": 300,
            "class": "Compo",
            "width": 88
        },
        {
            "column_max": 244,
            "row_min": 322,
            "height": 176,
            "id": null,
            "column_min": 6,
            "row_max": 497,
            "class": "Compo",
            "width": 239
        },
        {
            "column_max": 486,
            "row_min": 322,
            "height": 176,
            "id": null,
            "column_min": 248,
            "row_max": 497,
            "class": "Compo",
            "width": 239
        },
        {
            "column_max": 161,
            "row_min": 512,
            "height": 27,
            "id": null,
            "column_min": 141,
            "row_max": 538,
            "class": "Compo",
            "width": 21
        },
        {
            "column_max": 404,
            "row_min": 514,
            "height": 25,
            "id": null,
            "column_min": 383,
            "row_max": 538,
            "class": "Compo",
            "width": 22
        },
        {
            "column_max": 43,
            "row_min": 519,
            "height": 16,
            "id": null,
            "column_min": 10,
            "row_max": 534,
            "class": "Compo",
            "width": 34
        },
        {
            "column_max": 241,
            "row_min": 516,
            "height": 20,
            "id": null,
            "column_min": 167,
            "row_max": 535,
            "class": "Compo",
            "width": 75
        },
        {
            "column_max": 284,
            "row_min": 518,
            "height": 17,
            "id": null,
            "column_min": 252,
            "row_max": 534,
            "class": "Compo",
            "width": 33
        },
        {
            "column_max": 483,
            "row_min": 516,
            "height": 20,
            "id": null,
            "column_min": 409,
            "row_max": 535,
            "class": "Compo",
            "width": 75
        },
        {
            "column_max": 244,
            "row_min": 553,
            "height": 177,
            "id": null,
            "column_min": 6,
            "row_max": 729,
            "class": "Compo",
            "width": 239
        },
        {
            "column_max": 486,
            "row_min": 553,
            "height": 177,
            "id": null,
            "column_min": 248,
            "row_max": 729,
            "class": "Compo",
            "width": 239
        },
        {
            "column_max": 469,
            "row_min": 564,
            "height": 13,
            "id": null,
            "column_min": 458,
            "row_max": 576,
            "class": "Compo",
            "width": 12
        },
        {
            "column_max": 137,
            "row_min": 746,
            "height": 24,
            "id": null,
            "column_min": 109,
            "row_max": 769,
            "class": "Compo",
            "width": 29
        },
        {
            "column_max": 383,
            "row_min": 744,
            "height": 26,
            "id": null,
            "column_min": 356,
            "row_max": 769,
            "class": "Compo",
            "width": 28
        },
        {
            "column_max": 149,
            "row_min": 776,
            "height": 16,
            "id": null,
            "column_min": 94,
            "row_max": 791,
            "class": "Compo",
            "width": 56
        },
        {
            "column_max": 398,
            "row_min": 776,
            "height": 16,
            "id": null,
            "column_min": 343,
            "row_max": 791,
            "class": "Compo",
            "width": 56
        }
    ]
}