{
    "compos": [
        {
            "width": 498,
            "column_min": 0,
            "id": 0,
            "height": 800,
            "row_min": 0,
            "row_max": 800,
            "column_max": 498,
            "class": "Background"
        },
        {
            "width": 497,
            "column_min": 0,
            "id": null,
            "height": 477,
            "row_min": 4,
            "row_max": 480,
            "column_max": 496,
            "class": "Compo"
        },
        {
            "width": 55,
            "column_min": 328,
            "id": null,
            "height": 54,
            "row_min": 312,
            "row_max": 365,
            "column_max": 382,
            "class": "Compo"
        },
        {
            "width": 106,
            "column_min": 46,
            "id": null,
            "height": 105,
            "row_min": 510,
            "row_max": 614,
            "column_max": 151,
            "class": "Compo"
        },
        {
            "width": 205,
            "column_min": 171,
            "id": null,
            "height": 30,
            "row_min": 518,
            "row_max": 547,
            "column_max": 375,
            "class": "Compo"
        },
        {
            "width": 98,
            "column_min": 382,
            "id": null,
            "height": 31,
            "row_min": 518,
            "row_max": 548,
            "column_max": 479,
            "class": "Compo"
        },
        {
            "width": 41,
            "column_min": 331,
            "id": null,
            "height": 44,
            "row_min": 564,
            "row_max": 607,
            "column_max": 371,
            "class": "Compo"
        },
        {
            "width": 42,
            "column_min": 171,
            "id": null,
            "height": 41,
            "row_min": 567,
            "row_max": 607,
            "column_max": 212,
            "class": "Compo"
        },
        {
            "width": 41,
            "column_min": 225,
            "id": null,
            "height": 42,
            "row_min": 566,
            "row_max": 607,
            "column_max": 265,
            "class": "Compo"
        },
        {
            "width": 41,
            "column_min": 278,
            "id": null,
            "height": 40,
            "row_min": 568,
            "row_max": 607,
            "column_max": 318,
            "class": "Compo"
        },
        {
            "width": 40,
            "column_min": 384,
            "id": null,
            "height": 41,
            "row_min": 567,
            "row_max": 607,
            "column_max": 423,
            "class": "Compo"
        },
        {
            "width": 403,
            "column_min": 47,
            "id": null,
            "height": 73,
            "row_min": 666,
            "row_max": 738,
            "column_max": 449,
            "class": "Compo"
        },
        {
            "width": 33,
            "column_min": 161,
            "id": null,
            "height": 30,
            "row_min": 688,
            "row_max": 717,
            "column_max": 193,
            "class": "Compo"
        },
        {
            "width": 143,
            "column_min": 192,
            "id": null,
            "height": 30,
            "row_min": 688,
            "row_max": 717,
            "column_max": 334,
            "class": "Compo"
        }
    ]
}